MANIFEST.in
README.mkd
info.py
setup.py
ACCC.egg-info/PKG-INFO
ACCC.egg-info/SOURCES.txt
ACCC.egg-info/dependency_links.txt
ACCC.egg-info/not-zip-safe
ACCC.egg-info/top_level.txt
accc/__init__.py
accc/__init__.pyc
accc/__main__.py
accc/__pycache__/__init__.cpython-34.pyc
accc/__pycache__/__main__.cpython-34.pyc
accc/compiler/__init__.py
accc/compiler/__init__.pyc
accc/compiler/compiler.py
accc/compiler/compiler.pyc
accc/compiler/__pycache__/__init__.cpython-34.pyc
accc/compiler/__pycache__/compiler.cpython-34.pyc
accc/dnacompiler/__init__.py
accc/dnacompiler/dnacompiler.py
accc/dnacompiler/__pycache__/__init__.cpython-34.pyc
accc/dnacompiler/__pycache__/dnacompiler.cpython-34.pyc