Metadata-Version: 1.1
Name: ACCC
Version: 0.0.1
Summary: Always Correct Correctness Compilator
Home-page: https://github.com/Aluriak/ACCC
Author: aluriak
Author-email: lucas.bourneuf@laposte.net
License: UNKNOWN
Keywords: compilation compiler correctness
Platform: UNKNOWN
Classifier: License :: OSI Approved :: GNU General Public License (GPL)
Classifier: Natural Language :: English
Classifier: Operating System :: Unix
Classifier: Programming Language :: Python :: 3
Classifier: Topic :: Software Development :: Libraries :: Python Modules
Classifier: Topic :: Software Development :: Code Generators
Classifier: Topic :: Software Development :: Compilers
